<?xml version="1.0" encoding="UTF-8"?>
<games><game><name>Chess.com</name><stats><stat key="Rapid rating" value="841"/><stat key="Blitz rating" value="637"/><stat key="Tactics high" value="1524"/><stat key="Tactics low" value="387"/><stat key="chess_username" value="JardikR"/><stat key="chess_name" value="JardikR"/></stats></game><game><name>League of Legends</name><stats><stat key="tier" value="EMERALD"/><stat key="rank" value="I"/><stat key="wins" value="27"/><stat key="losses" value="23"/><stat key="riot_name" value="fuchio420"/><stat key="riot_tag" value="ZAZA"/><stat key="platform_region" value="EUN1"/><stat key="global_region" value="Europe"/></stats></game><game><name>Clash Royale</name><stats><stat key="player_name" value="Džara"/><stat key="player_tag" value="#2CJYVRGPC"/><stat key="trophies" value="5331"/><stat key="best_trophies" value="5544"/><stat key="wins" value="1214"/><stat key="losses" value="758"/><stat key="clan_name" value="Alkoholiků plno"/><stat key="royale_tag" value="#2CJYVRGPC"/></stats></game></games>
